shellock/__init__.py
shellock/api.py
shellock/cli.py
shellock/crypto.py
shellock/exceptions.py
shellock-0.1.2.dist-info/METADATA
shellock-0.1.2.dist-info/WHEEL
shellock-0.1.2.dist-info/entry_points.txt
shellock-0.1.2.dist-info/licenses/LICENSE
shellock-0.1.2.dist-info/RECORD
