Metadata-Version: 2.4
Name: shellock
Version: 0.1.2
Summary: Secure encryption for configuration files using AES-256-GCM + Argon2id
Project-URL: Homepage, https://github.com/Madan2248c/shellock
Project-URL: Documentation, https://github.com/Madan2248c/shellock#readme
Project-URL: Repository, https://github.com/Madan2248c/shellock
Project-URL: Bug Tracker, https://github.com/Madan2248c/shellock/issues
Author-email: Madan Gopal <madangopalboddu123@gmail.com>
License: MIT
License-File: LICENSE
Keywords: configuration,crypto,encryption,files,security
Classifier: Development Status :: 3 - Alpha
Classifier: Intended Audience :: Developers
Classifier: License :: OSI Approved :: MIT License
Classifier: Operating System :: OS Independent
Classifier: Programming Language :: Python :: 3
Classifier: Programming Language :: Python :: 3.8
Classifier: Programming Language :: Python :: 3.9
Classifier: Programming Language :: Python :: 3.10
Classifier: Programming Language :: Python :: 3.11
Classifier: Programming Language :: Python :: 3.12
Classifier: Topic :: Security :: Cryptography
Classifier: Topic :: Software Development :: Libraries :: Python Modules
Requires-Python: >=3.8
Requires-Dist: click>=8.0.0
Requires-Dist: cryptography>=41.0.0
Requires-Dist: rich>=13.0.0
Provides-Extra: dev
Requires-Dist: hypothesis>=6.0; extra == 'dev'
Requires-Dist: mypy>=1.0; extra == 'dev'
Requires-Dist: pre-commit>=3.0; extra == 'dev'
Requires-Dist: pytest-cov>=4.0; extra == 'dev'
Requires-Dist: pytest>=7.0; extra == 'dev'
Requires-Dist: ruff>=0.1.0; extra == 'dev'
Provides-Extra: secure
Requires-Dist: zeroize>=1.0.0; extra == 'secure'
